MANIFEST.in
README.txt
setup.py
docs/HISTORY.txt
src/dolmen/__init__.py
src/dolmen.collection.egg-info/PKG-INFO
src/dolmen.collection.egg-info/SOURCES.txt
src/dolmen.collection.egg-info/dependency_links.txt
src/dolmen.collection.egg-info/namespace_packages.txt
src/dolmen.collection.egg-info/not-zip-safe
src/dolmen.collection.egg-info/requires.txt
src/dolmen.collection.egg-info/top_level.txt
src/dolmen/collection/__init__.py
src/dolmen/collection/components.py
src/dolmen/collection/interfaces.py
src/dolmen/collection/load.py
src/dolmen/collection/sorters.py