Metadata-Version: 2.1
Name: dolmen.collection
Version: 0.5
Summary: Collection of named entities
Home-page: http://pypi.python.org/pypi/dolmen.collection
Author: Dolmen Team
Author-email: dolmen@list.dolmen-project.org
License: BSD
Keywords: collection library
Platform: UNKNOWN
Classifier: Programming Language :: Python
Classifier: Topic :: Software Development :: Libraries :: Python Modules
Provides-Extra: test
